codelife/__init__.py
codelife/aa.py
codelife/ab.py
codelife/event_handler.py
codelife/loopfiles.py
codelife/main.py
codelife/mainview.py
codelife/mainview2.py
codelife/menu_setting.py
codelife/notification.py
codelife/pip_trigger.py
codelife/project_item_creator.py
codelife/proxy_run.py
codelife/setting.py
codelife/store.py
codelife/tree.py
codelife/common/__init__.py
codelife/common/text_decorator.py
codelife/core/__init__.py
codelife/core/tree_node_render.py
codelife/generator/__init__.py
codelife/generator/dummy_generator.py
codelife/generator/generator.py
codelife/generator/generator_factory.py
codelife/generator/python_file_generator.py
codelife/generator/python_module_generator.py
codelife/generator/text_file_generator.py
codelife/uicore/__init__.py
codelife/uicore/editor_widgets.py
tests/__init__.py
tests/test_loopfiles.py
tests/test_main.py
codelife-0.0.5.dist-info/METADATA
codelife-0.0.5.dist-info/WHEEL
codelife-0.0.5.dist-info/entry_points.txt
codelife-0.0.5.dist-info/top_level.txt
codelife-0.0.5.dist-info/RECORD
